itkwasm_morphological_contour_interpolation_emscripten/__init__.py
itkwasm_morphological_contour_interpolation_emscripten/_version.py
itkwasm_morphological_contour_interpolation_emscripten/js_package.py
itkwasm_morphological_contour_interpolation_emscripten/morphological_contour_interpolation_async.py
itkwasm_morphological_contour_interpolation_emscripten-2.0.0.dist-info/METADATA
itkwasm_morphological_contour_interpolation_emscripten-2.0.0.dist-info/WHEEL
itkwasm_morphological_contour_interpolation_emscripten-2.0.0.dist-info/RECORD
