Metadata-Version: 2.4
Name: itkwasm-morphological-contour-interpolation-emscripten
Version: 2.0.0
Summary: Morphology-based approach for interslice interpolation of anatomical slices from volumetric images.
Project-URL: Home, https://github.com/KitwareMedical/ITKMorphologicalContourInterpolation
Project-URL: Source, https://github.com/KitwareMedical/ITKMorphologicalContourInterpolation
Keywords: emscripten,itkwasm,webassembly
Classifier: Development Status :: 4 - Beta
Classifier: Environment :: WebAssembly
Classifier: Environment :: WebAssembly :: Emscripten
Classifier: Environment :: WebAssembly :: WASI
Classifier: Intended Audience :: Developers
Classifier: Intended Audience :: Science/Research
Classifier: License :: OSI Approved :: Apache Software License
Classifier: Programming Language :: C++
Classifier: Programming Language :: Python
Classifier: Programming Language :: Python :: 3
Classifier: Programming Language :: Python :: 3.9
Classifier: Programming Language :: Python :: 3.10
Classifier: Programming Language :: Python :: 3.11
Classifier: Programming Language :: Python :: 3.12
Classifier: Programming Language :: Python :: 3.13
Requires-Python: >=3.8
Requires-Dist: itkwasm>=1.0.b184
